pcalc.py
pcalc-1.0.dist-info/DESCRIPTION.rst
pcalc-1.0.dist-info/METADATA
pcalc-1.0.dist-info/RECORD
pcalc-1.0.dist-info/WHEEL
pcalc-1.0.dist-info/entry_points.txt
pcalc-1.0.dist-info/metadata.json
pcalc-1.0.dist-info/top_level.txt
pcalc-1.0.dist-info/zip-safe
