Metadata-Version: 2.0
Name: pcalc
Version: 1.0
Summary: Basic math operations for Unix pipes.
Home-page: https://github.com/geowurster/pcalc
Author: Kevin Wurster
Author-email: wursterk@gmail.com
License: New BSD
Keywords: command line CLI math unix pipe
Platform: UNKNOWN
Classifier: Topic :: Utilities
Classifier: Development Status :: 1 - Planning
Classifier: Environment :: Console
Classifier: License :: OSI Approved :: BSD License
Classifier: Intended Audience :: Developers
Classifier: Intended Audience :: Information Technology
Classifier: Intended Audience :: Science/Research
Classifier: Topic :: Text Processing
Classifier: Topic :: Software Development :: Libraries
Classifier: Programming Language :: Python :: 2.7
Classifier: Programming Language :: Python :: 3.3
Classifier: Programming Language :: Python :: 3.4
Classifier: Programming Language :: Python :: 3.5
Classifier: Programming Language :: Python :: Implementation :: PyPy
Requires-Dist: click
Provides-Extra: all
Requires-Dist: coveralls; extra == 'all'
Requires-Dist: pytest (>=3); extra == 'all'
Requires-Dist: pytest-cov; extra == 'all'
Provides-Extra: dev
Requires-Dist: coveralls; extra == 'dev'
Requires-Dist: pytest (>=3); extra == 'dev'
Requires-Dist: pytest-cov; extra == 'dev'
